<?xml version="1.0" encoding="utf-8"?>
<annotation>
<size>
<width>800</width>
<height>800</height>
</size>
<object>
<name>Boeing787</name>
<pose>Unspecified</pose>
<truncated>0</truncated>
<difficult>0</difficult>
<bndbox>
<xmin>469</xmin>
<ymin>203</ymin>
<xmax>554</xmax>
<ymax>272</ymax>
</bndbox>
</object>
<object>
<name>Boeing737</name>
<pose>Unspecified</pose>
<truncated>0</truncated>
<difficult>0</difficult>
<bndbox>
<xmin>376</xmin>
<ymin>201</ymin>
<xmax>457</xmax>
<ymax>270</ymax>
</bndbox>
</object>
<object>
<name>Boeing737</name>
<pose>Unspecified</pose>
<truncated>0</truncated>
<difficult>0</difficult>
<bndbox>
<xmin>308</xmin>
<ymin>262</ymin>
<xmax>361</xmax>
<ymax>331</ymax>
</bndbox>
</object>
<object>
<name>Boeing737</name>
<pose>Unspecified</pose>
<truncated>0</truncated>
<difficult>0</difficult>
<bndbox>
<xmin>184</xmin>
<ymin>355</ymin>
<xmax>254</xmax>
<ymax>420</ymax>
</bndbox>
</object>
</annotation>