<?xml version="1.0" encoding="utf-8"?>
<annotation>
<size>
<width>1500</width>
<height>1500</height>
</size>
<object>
<name>Boeing787</name>
<pose>Unspecified</pose>
<truncated>0</truncated>
<difficult>0</difficult>
<bndbox>
<xmin>759</xmin>
<ymin>1236</ymin>
<xmax>859</xmax>
<ymax>1334</ymax>
</bndbox>
</object>
<object>
<name>other</name>
<pose>Unspecified</pose>
<truncated>0</truncated>
<difficult>0</difficult>
<bndbox>
<xmin>680</xmin>
<ymin>802</ymin>
<xmax>815</xmax>
<ymax>922</ymax>
</bndbox>
</object>
</annotation>