<?xml version="1.0" encoding="utf-8"?>
<annotation>
<size>
<width>1000</width>
<height>1000</height>
</size>
<object>
<name>Boeing787</name>
<pose>Unspecified</pose>
<truncated>0</truncated>
<difficult>0</difficult>
<bndbox>
<xmin>896</xmin>
<ymin>277</ymin>
<xmax>974</xmax>
<ymax>392</ymax>
</bndbox>
</object>
<object>
<name>Boeing737</name>
<pose>Unspecified</pose>
<truncated>0</truncated>
<difficult>0</difficult>
<bndbox>
<xmin>705</xmin>
<ymin>280</ymin>
<xmax>784</xmax>
<ymax>379</ymax>
</bndbox>
</object>
</annotation>