<?xml version="1.0" encoding="utf-8"?>
<annotation>
<size>
<width>1500</width>
<height>1500</height>
</size>
<object>
<name>other</name>
<pose>Unspecified</pose>
<truncated>0</truncated>
<difficult>0</difficult>
<bndbox>
<xmin>705</xmin>
<ymin>69</ymin>
<xmax>803</xmax>
<ymax>165</ymax>
</bndbox>
</object>
<object>
<name>Boeing787</name>
<pose>Unspecified</pose>
<truncated>0</truncated>
<difficult>0</difficult>
<bndbox>
<xmin>768</xmin>
<ymin>488</ymin>
<xmax>858</xmax>
<ymax>588</ymax>
</bndbox>
</object>
<object>
<name>other</name>
<pose>Unspecified</pose>
<truncated>0</truncated>
<difficult>0</difficult>
<bndbox>
<xmin>761</xmin>
<ymin>753</ymin>
<xmax>901</xmax>
<ymax>874</ymax>
</bndbox>
</object>
<object>
<name>other</name>
<pose>Unspecified</pose>
<truncated>0</truncated>
<difficult>0</difficult>
<bndbox>
<xmin>808</xmin>
<ymin>1036</ymin>
<xmax>942</xmax>
<ymax>1182</ymax>
</bndbox>
</object>
<object>
<name>other</name>
<pose>Unspecified</pose>
<truncated>0</truncated>
<difficult>0</difficult>
<bndbox>
<xmin>634</xmin>
<ymin>1333</ymin>
<xmax>792</xmax>
<ymax>1466</ymax>
</bndbox>
</object>
<object>
<name>A330</name>
<pose>Unspecified</pose>
<truncated>0</truncated>
<difficult>0</difficult>
<bndbox>
<xmin>859</xmin>
<ymin>1362</ymin>
<xmax>961</xmax>
<ymax>1447</ymax>
</bndbox>
</object>
<object>
<name>A220</name>
<pose>Unspecified</pose>
<truncated>0</truncated>
<difficult>0</difficult>
<bndbox>
<xmin>650</xmin>
<ymin>1055</ymin>
<xmax>729</xmax>
<ymax>1123</ymax>
</bndbox>
</object>
<object>
<name>other</name>
<pose>Unspecified</pose>
<truncated>0</truncated>
<difficult>0</difficult>
<bndbox>
<xmin>121</xmin>
<ymin>651</ymin>
<xmax>311</xmax>
<ymax>818</ymax>
</bndbox>
</object>
</annotation>