<?xml version="1.0" encoding="utf-8"?>
<annotation>
<size>
<width>1500</width>
<height>1500</height>
</size>
<object>
<name>A220</name>
<pose>Unspecified</pose>
<truncated>0</truncated>
<difficult>0</difficult>
<bndbox>
<xmin>845</xmin>
<ymin>161</ymin>
<xmax>945</xmax>
<ymax>240</ymax>
</bndbox>
</object>
<object>
<name>A330</name>
<pose>Unspecified</pose>
<truncated>0</truncated>
<difficult>0</difficult>
<bndbox>
<xmin>1205</xmin>
<ymin>433</ymin>
<xmax>1306</xmax>
<ymax>519</ymax>
</bndbox>
</object>
</annotation>