<?xml version="1.0" encoding="utf-8"?>
<annotation>
<size>
<width>1500</width>
<height>1500</height>
</size>
<object>
<name>other</name>
<pose>Unspecified</pose>
<truncated>0</truncated>
<difficult>0</difficult>
<bndbox>
<xmin>1324</xmin>
<ymin>432</ymin>
<xmax>1439</xmax>
<ymax>553</ymax>
</bndbox>
</object>
<object>
<name>A220</name>
<pose>Unspecified</pose>
<truncated>0</truncated>
<difficult>0</difficult>
<bndbox>
<xmin>1241</xmin>
<ymin>455</ymin>
<xmax>1320</xmax>
<ymax>556</ymax>
</bndbox>
</object>
<object>
<name>Boeing737</name>
<pose>Unspecified</pose>
<truncated>0</truncated>
<difficult>0</difficult>
<bndbox>
<xmin>1191</xmin>
<ymin>171</ymin>
<xmax>1287</xmax>
<ymax>283</ymax>
</bndbox>
</object>
<object>
<name>A220</name>
<pose>Unspecified</pose>
<truncated>0</truncated>
<difficult>0</difficult>
<bndbox>
<xmin>1006</xmin>
<ymin>224</ymin>
<xmax>1105</xmax>
<ymax>297</ymax>
</bndbox>
</object>
<object>
<name>A220</name>
<pose>Unspecified</pose>
<truncated>0</truncated>
<difficult>0</difficult>
<bndbox>
<xmin>993</xmin>
<ymin>153</ymin>
<xmax>1088</xmax>
<ymax>219</ymax>
</bndbox>
</object>
</annotation>