<?xml version="1.0" encoding="utf-8"?>
<annotation>
<size>
<width>1000</width>
<height>1000</height>
</size>
<object>
<name>Boeing787</name>
<pose>Unspecified</pose>
<truncated>0</truncated>
<difficult>0</difficult>
<bndbox>
<xmin>592</xmin>
<ymin>66</ymin>
<xmax>709</xmax>
<ymax>189</ymax>
</bndbox>
</object>
<object>
<name>Boeing737</name>
<pose>Unspecified</pose>
<truncated>0</truncated>
<difficult>0</difficult>
<bndbox>
<xmin>498</xmin>
<ymin>188</ymin>
<xmax>584</xmax>
<ymax>281</ymax>
</bndbox>
</object>
</annotation>