<?xml version="1.0" encoding="utf-8"?>
<annotation>
<size>
<width>800</width>
<height>800</height>
</size>
<object>
<name>A220</name>
<pose>Unspecified</pose>
<truncated>0</truncated>
<difficult>0</difficult>
<bndbox>
<xmin>152</xmin>
<ymin>308</ymin>
<xmax>248</xmax>
<ymax>376</ymax>
</bndbox>
</object>
<object>
<name>A220</name>
<pose>Unspecified</pose>
<truncated>0</truncated>
<difficult>0</difficult>
<bndbox>
<xmin>158</xmin>
<ymin>229</ymin>
<xmax>237</xmax>
<ymax>294</ymax>
</bndbox>
</object>
<object>
<name>A220</name>
<pose>Unspecified</pose>
<truncated>0</truncated>
<difficult>0</difficult>
<bndbox>
<xmin>137</xmin>
<ymin>143</ymin>
<xmax>252</xmax>
<ymax>221</ymax>
</bndbox>
</object>
</annotation>